LICENSE.txt
MANIFEST.in
README.rst
setup.cfg
setup.py
tw2/__init__.py
tw2.jqplugins.jqplot.egg-info/PKG-INFO
tw2.jqplugins.jqplot.egg-info/SOURCES.txt
tw2.jqplugins.jqplot.egg-info/dependency_links.txt
tw2.jqplugins.jqplot.egg-info/entry_points.txt
tw2.jqplugins.jqplot.egg-info/namespace_packages.txt
tw2.jqplugins.jqplot.egg-info/not-zip-safe
tw2.jqplugins.jqplot.egg-info/requires.txt
tw2.jqplugins.jqplot.egg-info/top_level.txt
tw2/jqplugins/__init__.py
tw2/jqplugins/jqplot/__init__.py
tw2/jqplugins/jqplot/base.py
tw2/jqplugins/jqplot/defaults.py
tw2/jqplugins/jqplot/samples.py
tw2/jqplugins/jqplot/widgets.py
tw2/jqplugins/jqplot/static/jquery/plugins/jqplot/0.9.7r635/MIT-LICENSE.txt
tw2/jqplugins/jqplot/static/jquery/plugins/jqplot/0.9.7r635/README.txt
tw2/jqplugins/jqplot/static/jquery/plugins/jqplot/0.9.7r635/changes.txt
tw2/jqplugins/jqplot/static/jquery/plugins/jqplot/0.9.7r635/copyright.txt
tw2/jqplugins/jqplot/static/jquery/plugins/jqplot/0.9.7r635/excanvas.js
tw2/jqplugins/jqplot/static/jquery/plugins/jqplot/0.9.7r635/excanvas.min.js
tw2/jqplugins/jqplot/static/jquery/plugins/jqplot/0.9.7r635/gpl-2.0.txt
tw2/jqplugins/jqplot/static/jquery/plugins/jqplot/0.9.7r635/jqPlotCssStyling.txt
tw2/jqplugins/jqplot/static/jquery/plugins/jqplot/0.9.7r635/jqPlotOptions.txt
tw2/jqplugins/jqplot/static/jquery/plugins/jqplot/0.9.7r635/jquery-1.4.1.min.js
tw2/jqplugins/jqplot/static/jquery/plugins/jqplot/0.9.7r635/jquery-1.4.2.min.js
tw2/jqplugins/jqplot/static/jquery/plugins/jqplot/0.9.7r635/jquery.jqplot.css
tw2/jqplugins/jqplot/static/jquery/plugins/jqplot/0.9.7r635/jquery.jqplot.js
tw2/jqplugins/jqplot/static/jquery/plugins/jqplot/0.9.7r635/jquery.jqplot.min.css
tw2/jqplugins/jqplot/static/jquery/plugins/jqplot/0.9.7r635/jquery.jqplot.min.js
tw2/jqplugins/jqplot/static/jquery/plugins/jqplot/0.9.7r635/optionsTutorial.txt
tw2/jqplugins/jqplot/static/jquery/plugins/jqplot/0.9.7r635/usage.txt
tw2/jqplugins/jqplot/static/jquery/plugins/jqplot/0.9.7r635/docs/index.html
tw2/jqplugins/jqplot/static/jquery/plugins/jqplot/0.9.7r635/docs/files/MIT-LICENSE-txt.html
tw2/jqplugins/jqplot/static/jquery/plugins/jqplot/0.9.7r635/docs/files/changes-txt.html
tw2/jqplugins/jqplot/static/jquery/plugins/jqplot/0.9.7r635/docs/files/gpl-2-0-txt.html
tw2/jqplugins/jqplot/static/jquery/plugins/jqplot/0.9.7r635/docs/files/jqPlotCssStyling-txt.html
